setup.py
pydecors/__init__.py
pydecors/decors.py
pydecors.egg-info/PKG-INFO
pydecors.egg-info/SOURCES.txt
pydecors.egg-info/dependency_links.txt
pydecors.egg-info/not-zip-safe
pydecors.egg-info/top_level.txt