Metadata-Version: 2.1
Name: pydecors
Version: 0.0.2
Summary: 一些好用的装饰器
Author: WangTuo
Author-email: markadc@126.com
License: MIT
